<?xml version="1.0" encoding="UTF-8" standalone="yes"?>
<Inductance xmlns:xsi="http://www.w3.org/2001/XMLSchema-instance">
	<Part>
		<PartNumber>Inductance</PartNumber>
		<Description>Катушка индуктивности</Description>
		<Comment>Inductance</Comment>
		<FootprintPath1>Footprints\Inductance\0603L.PcbLib</FootprintPath1>
		<FootprintRef1>0603L</FootprintRef1>
		<FootprintPath2>Footprints\Inductance\1210L.PcbLib</FootprintPath2>
		<FootprintRef2>1210L</FootprintRef2>
		<FootprintPath3>Footprints\Inductance\1212L.PcbLib</FootprintPath3>
		<FootprintRef3>1212L</FootprintRef3>
		<FootprintPath4>Footprints\Inductance\12.8x12.8.PcbLib</FootprintPath4>
		<FootprintRef4>12.8x12.8</FootprintRef4>
	</Part>
	<Part>
		<PartNumber>IHLP4040DZER330M11</PartNumber>
		<Description>ЧИП-индуктивность экранированная 33мкГн ±20% 4,4A 94,5мОм 4040</Description>
		<Comment>IHLP4040DZER330M11</Comment>
		<FootprintPath1>Footprints\Inductance\IHLP-4040.PcbLib</FootprintPath1>
		<FootprintRef1>IHLP-4040</FootprintRef1>
		<Inductance>33</Inductance>
		<Current>4.4</Current>
		<Value>33 мк</Value>
	</Part>
	<Part>
		<PartNumber>B82472G6683M</PartNumber>
		<Description>Индуктивность на 68 мкГн, номинальный ток 0,82 A</Description>
		<Comment>B82472G6683M</Comment>
		<FootprintPath1>Footprints\Inductance\7.3x7.3.PcbLib</FootprintPath1>
		<FootprintRef1>7.3x7.3</FootprintRef1>
		<Inductance>68</Inductance>
		<Current>0.82</Current>
		<Value>68 мк</Value>
	</Part>
	<Part>
		<PartNumber>IHLP2525CZER4R7M01</PartNumber>
		<Description>ЧИП-индуктивность экранированная 4,7мкГн ±20% 5,5A 40мОм 2525</Description>
		<Comment>IHLP2525CZER4R7M01</Comment>
		<FootprintPath1>Footprints\Inductance\IHLP-2525.PcbLib</FootprintPath1>
		<FootprintRef1>IHLP-2525</FootprintRef1>
		<FootprintPath2>Footprints\Inductance\.PcbLib</FootprintPath2>
		<FootprintPath3>Footprints\Inductance\.PcbLib</FootprintPath3>
		<FootprintPath4>Footprints\Inductance\.PcbLib</FootprintPath4>
		<Inductance>4.7</Inductance>
		<Current>5.5</Current>
		<Value>4,7 мк</Value>
	</Part>
	<Part>
		<PartNumber>IHLP4040DZER220M11</PartNumber>
		<Description>ЧИП-индуктивность экранированная 22мкГн ±20% 5A 66мОм 4040 лента на катушке</Description>
		<Comment>IHLP4040DZER220M11</Comment>
		<FootprintPath1>Footprints\Inductance\IHLP-4040.PcbLib</FootprintPath1>
		<FootprintRef1>IHLP-4040</FootprintRef1>
		<FootprintPath2>Footprints\Inductance\.PcbLib</FootprintPath2>
		<FootprintPath3>Footprints\Inductance\.PcbLib</FootprintPath3>
		<FootprintPath4>Footprints\Inductance\.PcbLib</FootprintPath4>
		<Inductance>22</Inductance>
		<Current>5</Current>
		<Value>22 мк</Value>
	</Part>
</Inductance>