<?xml version="1.0" encoding="UTF-8" standalone="yes"?>
<Other xmlns:xsi="http://www.w3.org/2001/XMLSchema-instance">
	<Part>
		<PartNumber>Tact_button</PartNumber>
		<Description>Тактовая кнопка</Description>
		<Comment>Tact_button</Comment>
		<LibraryPath>Schematic\Tact_button.SchLib</LibraryPath>
		<LibraryRef>Tact_button</LibraryRef>
		<FootprintPath1>Footprints\Buttons\Button_SMD_10mm.PcbLib</FootprintPath1>
		<FootprintRef1>Button_SMD_10mm</FootprintRef1>
		<FootprintPath2>Footprints\Buttons\Button_SMD_6x6.PcbLib</FootprintPath2>
		<FootprintRef2>Button_SMD_6x6</FootprintRef2>
	</Part>
	<Part>
		<PartNumber>LED</PartNumber>
		<Description>Светодиод</Description>
		<Comment>LED</Comment>
		<LibraryPath>Schematic\LED.SchLib</LibraryPath>
		<LibraryRef>LED</LibraryRef>
		<FootprintPath1>Footprints\LED_SMD.PcbLib</FootprintPath1>
		<FootprintRef1>LED_SMD</FootprintRef1>
	</Part>
	<Part>
		<PartNumber>XTAL</PartNumber>
		<Description>Кварцевый резонатор</Description>
		<Comment>XTAL</Comment>
		<LibraryPath>Schematic\XTAL.SchLib</LibraryPath>
		<LibraryRef>XTAL</LibraryRef>
	</Part>
	<Part>
		<PartNumber>XTAL_GND</PartNumber>
		<Description>Кварцевый резонатор с входом земли</Description>
		<Comment>XTAL_GND</Comment>
		<LibraryPath>Schematic\XTAL_GND.SchLib</LibraryPath>
		<LibraryRef>XTAL_GND</LibraryRef>
		<FootprintPath1>Footprints\QSMD3.2x2.5.PcbLib</FootprintPath1>
		<FootprintRef1>QSMD3.2x2.5</FootprintRef1>
	</Part>
</Other>